README.rst
setup.py
har_api/__init__.py
har_api/models.py
har_api/resource_fields.py
har_api/routes.py
har_api/settings.py
har_api/utils.py
har_api/resources/__init__.py
har_api/resources/pages.py
har_api/resources/tests.py
haralyzer_api.egg-info/PKG-INFO
haralyzer_api.egg-info/SOURCES.txt
haralyzer_api.egg-info/dependency_links.txt
haralyzer_api.egg-info/pbr.json
haralyzer_api.egg-info/requires.txt
haralyzer_api.egg-info/top_level.txt