Metadata-Version: 1.1
Name: haralyzer-api
Version: 0.1
Summary: REST API for storing HAR data and retrieving analyzed results
Home-page: https://github.com/mrname/haralyzer-api
Author: Justin Crown
Author-email: admin@humanssuck.net
License: MIT
Platform: UNKNOWN
Classifier: Development Status :: 3 - Alpha
Classifier: Environment :: Web Environment
Classifier: License :: OSI Approved :: MIT License
Classifier: Natural Language :: English
Classifier: Operating System :: OS Independent
Classifier: Programming Language :: Python :: 2
Classifier: Programming Language :: Python :: 2.6
Classifier: Programming Language :: Python :: 2.7
Classifier: Programming Language :: Python :: 3
Classifier: Programming Language :: Python :: 3.3
Classifier: Programming Language :: Python :: 3.4
